vac_exporter/__init__.py
vac_exporter/defer.py
vac_exporter/vac_cli.py
vac_exporter/vac_exporter.py
vac_exporter/vac_http.py
vac_exporter-0.0.1.dist-info/LICENSE
vac_exporter-0.0.1.dist-info/METADATA
vac_exporter-0.0.1.dist-info/WHEEL
vac_exporter-0.0.1.dist-info/entry_points.txt
vac_exporter-0.0.1.dist-info/top_level.txt
vac_exporter-0.0.1.dist-info/RECORD
