Metadata-Version: 2.1
Name: vac-exporter
Version: 0.0.1
Summary: Veeam VAC Exporter for Prometheus
Home-page: https://gitlab.com/frenchtoasters/vac_exporter
Author: Tyler French
Author-email: UNKNOWN
License: BSD 3-Clause License
Keywords: Veeam,VAC,Prometheus
Platform: UNKNOWN
Requires-Dist: prometheus-client (==0.0.19)
Requires-Dist: pytz
Requires-Dist: twisted (>=14.0.2)
Requires-Dist: yamlconfig
Requires-Dist: service-identity
Requires-Dist: requests
Requires-Dist: Werkzeug
